fut_listen/__init__.py
fut_listen/assets/A5.mp3
fut_listen/assets/E6.mp3
fut_listen/assets/audio_play_1.m4a
fut_listen/assets/audio_play_2.m4a
fut_listen/assets/audio_play_3.m4a
fut_listen/assets/audio_play_4.m4a
fut_listen/assets/audio_play_5.m4a
fut_listen/assets/before_we_start_listening_you_can_read_the_questions.m4a
fut_listen/assets/good_job.m4a
fut_listen/assets/listening_number_1.m4a
fut_listen/assets/listening_number_10.m4a
fut_listen/assets/listening_number_2.m4a
fut_listen/assets/listening_number_3.m4a
fut_listen/assets/listening_number_4.m4a
fut_listen/assets/listening_number_5.m4a
fut_listen/assets/listening_number_6.m4a
fut_listen/assets/listening_number_7.m4a
fut_listen/assets/listening_number_8.m4a
fut_listen/assets/listening_number_9.m4a
fut_listen/assets/now_starting_the_listening_section_of_the_test.m4a
fut_listen/assets/the_listening_section_is_finished.m4a
fut_listen/cli.py
fut_listen-0.4.0.dist-info/LICENSE
fut_listen-0.4.0.dist-info/WHEEL
fut_listen-0.4.0.dist-info/entry_points.txt
fut_listen-0.4.0.dist-info/METADATA
fut_listen-0.4.0.dist-info/RECORD
