Metadata-Version: 2.1
Name: fut-listen
Version: 0.4.0
Summary: CLI Program to automate listening sections for tests.
Author: Dan Cook
Author-email: cook.r.dan@gmail.com
Requires-Python: >=3.10,<4.0
Classifier: Programming Language :: Python :: 3
Classifier: Programming Language :: Python :: 3.10
Classifier: Programming Language :: Python :: 3.11
Requires-Dist: click (>=8.1.7,<9.0.0)
